flowplot/__init__.py
flowplot/cycles.py
flowplot-0.0.15.dist-info/licenses/LICENSE
flowplot-0.0.15.dist-info/METADATA
flowplot-0.0.15.dist-info/WHEEL
flowplot-0.0.15.dist-info/top_level.txt
flowplot-0.0.15.dist-info/RECORD
