Metadata-Version: 2.4
Name: flowplot
Version: 0.0.15
Summary: An interactive visualisation ananlyis tool for flow and input-output-storage data
Author-email: Mikhail Smilovic <smilovic@mail.com>
License-Expression: GPL-3.0-or-later
Project-URL: Homepage, https://github.com/mikhailsmilovic/flowplot
Project-URL: Repository, https://github.com/mikhailsmilovic/flowplot
Project-URL: Issues, https://github.com/mikhailsmilovic/flowplot/issues
Keywords: hydrology,visualization,reservoir,plot,interactive
Classifier: Development Status :: 4 - Beta
Classifier: Programming Language :: Python :: 3
Classifier: Operating System :: OS Independent
Classifier: Intended Audience :: Science/Research
Classifier: Topic :: Scientific/Engineering :: Visualization
Requires-Python: >=3.7
License-File: LICENSE
Requires-Dist: numpy>=2.1.2
Requires-Dist: plotly>=5.24.0
Requires-Dist: pandas>=2.2.3
Dynamic: license-file
